lacrosse_view/__init__.py
lacrosse_view/const.py
lacrosse_view/py.typed
lacrosse_view/util.py
lacrosse_view-1.1.0.dist-info/LICENSE
lacrosse_view-1.1.0.dist-info/METADATA
lacrosse_view-1.1.0.dist-info/WHEEL
lacrosse_view-1.1.0.dist-info/top_level.txt
lacrosse_view-1.1.0.dist-info/RECORD
