Metadata-Version: 2.2
Name: lacrosse_view
Version: 1.1.0
Summary: Client for retrieving data from the La Crosse View cloud
Home-page: https://github.com/IceBotYT/lacrosse_view
Author: IceBotYT
Author-email: icebotyt@outlook.com
Project-URL: Bug Tracker, https://github.com/IceBotYT/lacrosse_view/issues
Classifier: Programming Language :: Python :: 3
Classifier: License :: OSI Approved :: MIT License
Classifier: Operating System :: OS Independent
Requires-Python: >=3.6
License-File: LICENSE
Requires-Dist: aiohttp>=3.8.1
Requires-Dist: pydantic<3.0.0,>=1.9.0
Requires-Dist: aiozoneinfo>=0.2.1
